{"sepolia": 
    {"lenderVault": "0xaF412a78e13F6b8FFBD6e73DfcF1030548321925", "quoteHandler": "0x7c4De582D228b58b72b2b6B2B36D95f27b47367a", "onChainQuotesToBeDeleted": 
    [ {"onChainQuoteHash": "0x1aa58676ffa3346ce9c0c0abd78f4689d708b24ef8252cd10d66b59e23783e34", "onChainQuote":
        {"generalQuoteInfo": {
            "collToken": "0x46a045b6E158CC6e0184f3773cea69c8f7E0A0cc",
            "loanToken": "0x3564c06EfEe0FeB0af5EF59dc5440bC45A265dA5",
            "oracleAddr": "0x0000000000000000000000000000000000000000",
            "minLoan": "1000",
            "maxLoan": "1000000000000000000000000",
            "validUntil": "1704018884",
            "earliestRepayTenor": 0,
            "borrowerCompartmentImplementation": "0x0000000000000000000000000000000000000000",
            "isSingleUse": false,
            "whitelistAddr": "0x0000000000000000000000000000000000000000",
            "isWhitelistAddrSingleBorrower": false
        }, "salt": "0x0000000000000000000000000000000000000000000000000000000000000000",
        "quoteTuples":
               [{"loanPerCollUnitOrLtv": "510000000000000000", "interestRatePctInBase": "0", "upfrontFeePctInBase": "416488105963998", "tenor": "2628000"}, {"loanPerCollUnitOrLtv": "510000000000000000", "interestRatePctInBase": "0", "upfrontFeePctInBase": "936616638418089", "tenor": "5913000"}, {"loanPerCollUnitOrLtv": "510000000000000000", "interestRatePctInBase": "0", "upfrontFeePctInBase": "1456203687448989", "tenor": "9198000"}, {"loanPerCollUnitOrLtv": "510000000000000000", "interestRatePctInBase": "0", "upfrontFeePctInBase": "1975249740468463", "tenor": "12483000"}, {"loanPerCollUnitOrLtv": "510000000000000000", "interestRatePctInBase": "0", "upfrontFeePctInBase": "2493755365861588", "tenor": "15768000"}, {"loanPerCollUnitOrLtv": "624750000000000000", "interestRatePctInBase": "0", "upfrontFeePctInBase": "510199052218144", "tenor": "2628000"}, {"loanPerCollUnitOrLtv": "624750000000000000", "interestRatePctInBase": "0", "upfrontFeePctInBase": "1147356512398793", "tenor": "5913000"}, {"loanPerCollUnitOrLtv": "624750000000000000", "interestRatePctInBase": "0", "upfrontFeePctInBase": "1783850593629971", "tenor": "9198000"}, {"loanPerCollUnitOrLtv": "624750000000000000", "interestRatePctInBase": "0", "upfrontFeePctInBase": "2419682043960554", "tenor": "12483000"}, {"loanPerCollUnitOrLtv": "624750000000000000", "interestRatePctInBase": "0", "upfrontFeePctInBase": "3054851463726623", "tenor": "15768000"}, {"loanPerCollUnitOrLtv": "739499999999999872", "interestRatePctInBase": "0", "upfrontFeePctInBase": "603910000611667", "tenor": "2628000"}, {"loanPerCollUnitOrLtv": "739499999999999872", "interestRatePctInBase": "0", "upfrontFeePctInBase": "1358096352629153", "tenor": "5913000"}, {"loanPerCollUnitOrLtv": "739499999999999872", "interestRatePctInBase": "0", "upfrontFeePctInBase": "2111497538886344", "tenor": "9198000"}, {"loanPerCollUnitOrLtv": "739499999999999872", "interestRatePctInBase": "0", "upfrontFeePctInBase": "2864114300092620", "tenor": "12483000"}, {"loanPerCollUnitOrLtv": "739499999999999872", "interestRatePctInBase": "0", "upfrontFeePctInBase": "3615947515232229", "tenor": "15768000"}, {"loanPerCollUnitOrLtv": "854250000000000000", "interestRatePctInBase": "0", "upfrontFeePctInBase": "697620941631572", "tenor": "2628000"}, {"loanPerCollUnitOrLtv": "854250000000000000", "interestRatePctInBase": "0", "upfrontFeePctInBase": "1568836234639220", "tenor": "5913000"}, {"loanPerCollUnitOrLtv": "854250000000000000", "interestRatePctInBase": "0", "upfrontFeePctInBase": "2439146658745508", "tenor": "9198000"}, {"loanPerCollUnitOrLtv": "854250000000000000", "interestRatePctInBase": "0", "upfrontFeePctInBase": "3308546708269622", "tenor": "12483000"}, {"loanPerCollUnitOrLtv": "854250000000000000", "interestRatePctInBase": "0", "upfrontFeePctInBase": "4177045073512393", "tenor": "15768000"}, {"loanPerCollUnitOrLtv": "969000000000000000", "interestRatePctInBase": "0", "upfrontFeePctInBase": "791992906713405", "tenor": "2628000"}, {"loanPerCollUnitOrLtv": "969000000000000000", "interestRatePctInBase": "0", "upfrontFeePctInBase": "1842164434977752", "tenor": "5913000"}, {"loanPerCollUnitOrLtv": "969000000000000000", "interestRatePctInBase": "0", "upfrontFeePctInBase": "3061396752403463", "tenor": "9198000"}, {"loanPerCollUnitOrLtv": "969000000000000000", "interestRatePctInBase": "0", "upfrontFeePctInBase": "4437842715155177", "tenor": "12483000"}, {"loanPerCollUnitOrLtv": "969000000000000000", "interestRatePctInBase": "0", "upfrontFeePctInBase": "5929748776109948", "tenor": "15768000"}]
        }}
    ]
    }
}



